README.rst
setup.py
bang/__init__.py
bang/__main__.py
bang/bangfile.py
bang/config.py
bang/event.py
bang/generator.py
bang/path.py
bang/server.py
bang/skeleton.py
bang/types.py
bang/utils.py
bang/md/__init__.py
bang/md/extensions/__init__.py
bang/md/extensions/absolutelink.py
bang/md/extensions/delins.py
bang/md/extensions/domevent.py
bang/md/extensions/embed.py
bang/md/extensions/highlight.py
bang/md/extensions/image.py
bang/md/extensions/magicref.py
bang/md/extensions/reference.py
bang/plugins/__init__.py
bang/plugins/core.py
bang/plugins/feed.py
bang/plugins/sitemap.py
bangtext.egg-info/PKG-INFO
bangtext.egg-info/SOURCES.txt
bangtext.egg-info/dependency_links.txt
bangtext.egg-info/entry_points.txt
bangtext.egg-info/requires.txt
bangtext.egg-info/top_level.txt
tests/__init__.py
tests/bang_test.py
tests/config_test.py
tests/event_test.py
tests/types_test.py